[
  {"insert":"你好，世界","attributes":{"author":"7743577"}},
  {"insert":1,"attributes":{"frag":"end"}},
  {"insert":"Hello Word","attributes":{"author":"7743577"}},
  {"insert":1,"attributes":{"frag":"end","block":"quote"}},

  {"insert":1,"attributes":{"frag":"end","block":"para"}},
  {"insert":"会尽快好好就开会开会开两会空间和孔令辉开空间还看过纠结开关机就看过看过就赶快公交卡钢结构和公交卡还感觉","attributes":{"author":"7743577"}},
  {"insert":1,"attributes":{"frag":"end","block":"quote"}},

  {"insert":"刽计划经济开会了","attributes":{"author":"7743577"}},
  {"insert":1,"attributes":{"frag":"end","block":"para"}},
  {"insert":1,"attributes":{"frag":"end","block":"para"}},
  {"insert":"皮卡丘","attributes":{"author":"7743577"}},
  {"insert":1,"attributes":{"frag":"end","block":"para"}},

  {"insert":"list 1","attributes":{"author":"7743577","size":"11"}},
  {"insert":1,"attributes":{"frag":"end","size":"11","list-id":"arym","list-type":"decimal","block":"list"}},
  {"insert":"list 2","attributes":{"author":"7743577","size":"11"}},
  {"insert":1,"attributes":{"frag":"end","size":"11","list-id":"arym","list-type":"decimal","block":"list"}},
  {"insert":"list 2.1","attributes":{"author":"7743577","size":"11"}},
  {"insert":1,"attributes":{"frag":"end","size":"11","indent":1,"author-block":"7743577","list-id":"arym","list-type":"decimal","block":"list"}},
  {"insert":"list 3","attributes":{"author":"7743577","size":"11"}},
  {"insert":1,"attributes":{"frag":"end","size":"11","list-id":"arym","list-type":"decimal","block":"list"}},
  {"insert":"list ul 1","attributes":{"author":"7743577"}},
  {"insert":1,"attributes":{"frag":"end","list-id":"zghf","list-type":"circle","block":"list"}},
  {"insert":"list 1.1","attributes":{"author":"7743577"}},
  {"insert":1,"attributes":{"frag":"end","indent":1,"list-id":"zghf","list-type":"circle","block":"list"}},
  {"insert":"list ul 2","attributes":{"author":"7743577"}},
  {"insert":1,"attributes":{"frag":"end","list-id":"zghf","list-type":"circle","block":"list"}},
  {"insert":"list ul 3","attributes":{"author":"7743577"}},
  {"insert":1,"attributes":{"frag":"end","list-id":"zghf","list-type":"circle","block":"list"}},

  {"insert":1,"attributes":{"frag":"end","block":"para"}},
  {"insert":"ABCDEFGHIJKLMNOPQRSTUVWXYZabcdefghijklmnopqrstuvwxyz","attributes":{"author":"7743577"}},
  {"insert":1,"attributes":{"frag":"end","block":"para"}},
  {"insert":"abcdefghijklmnopqrstuvwxyz","attributes":{"author":"7743577"}},
  {"insert":1,"attributes":{"frag":"end","block":"para"}},
  {"insert":"end end end end end end end end end end end end end end end ","attributes":{"author":"7743577"}},
  {"insert":1,"attributes":{"frag":"end","block":"para"}},
  {"insert":1,"attributes":{"frag":"end","block":"para"}},

  {"insert":"111","attributes":{"author":"7743577"}},
  {"insert":1,"attributes":{"frag":"end","list-id":"DfRJ","list-type":"decimal","block":"list"}},
  {"insert":"222","attributes":{"author":"7743577"}},
  {"insert":1,"attributes":{"frag":"end","list-id":"DfRJ","list-type":"decimal","block":"list"}},
  {"insert":"333","attributes":{"author":"7743577"}},
  {"insert":1,"attributes":{"frag":"end","indent":1,"list-id":"DfRJ","list-start":"3","list-type":"decimal","block":"list"}},
  {"insert":"444","attributes":{"author":"7743577"}},
  {"insert":1,"attributes":{"frag":"end","list-id":"DfRJ","list-type":"decimal","block":"list"}},

  {"insert":1,"attributes":{"frag":"end","block":"para"}},
  {"insert":1,"attributes":{"frag":"end","block":"para"}},
  {"insert":1,"attributes":{"frag":"end","block":"para"}},
  {"insert":"ggg","attributes":{"author":"7743577"}},
  {"insert":1,"attributes":{"frag":"end","list-id":"V4Ay","list-type":"decimal","block":"list"}},
  {"insert":"ggg","attributes":{"author":"7743577"}},
  {"insert":1,"attributes":{"frag":"end","list-id":"V4Ay","list-type":"decimal","block":"list"}},
  {"insert":"kjj","attributes":{"author":"7743577"}},
  {"insert":1,"attributes":{"frag":"end","list-id":"IllS","list-type":"decimal","block":"list"}},

  {"insert":1,"attributes":{"frag":"end","block":"para"}},
  {"insert":1,"attributes":{"frag":"end","block":"para"}},
  {"insert":"qqq","attributes":{"author":"7743577"}},
  {"insert":1,"attributes":{"frag":"end","indent":1,"list-id":"kRvb","list-type":"decimal","block":"list"}},
  {"insert":"hjghjkg","attributes":{"author":"7743577"}},
  {"insert":1,"attributes":{"frag":"end","block":"para"}}]